MANIFEST.in
README.md
setup.py
openbot_training_frontend/__init__.py
openbot_training_frontend/asset-manifest.json
openbot_training_frontend/favicon.ico
openbot_training_frontend/index.html
openbot_training_frontend/logo192.png
openbot_training_frontend/logo512.png
openbot_training_frontend/manifest.json
openbot_training_frontend/robots.txt
openbot_training_frontend.egg-info/PKG-INFO
openbot_training_frontend.egg-info/SOURCES.txt
openbot_training_frontend.egg-info/dependency_links.txt
openbot_training_frontend.egg-info/not-zip-safe
openbot_training_frontend.egg-info/top_level.txt
openbot_training_frontend/static/css/main.3e7deddd.css
openbot_training_frontend/static/css/main.3e7deddd.css.map
openbot_training_frontend/static/js/422.4a624484.chunk.js
openbot_training_frontend/static/js/422.4a624484.chunk.js.map
openbot_training_frontend/static/js/main.ce24a24d.js
openbot_training_frontend/static/js/main.ce24a24d.js.LICENSE.txt
openbot_training_frontend/static/js/main.ce24a24d.js.map